sysbenchinfo/__init__.py
sysbenchinfo/sys_info.py
SysBenchInfo-0.1.2.dist-info/METADATA
SysBenchInfo-0.1.2.dist-info/WHEEL
SysBenchInfo-0.1.2.dist-info/top_level.txt
SysBenchInfo-0.1.2.dist-info/RECORD
