Metadata-Version: 2.1
Name: SysBenchInfo
Version: 0.1.2
Summary: A package to get system information and benchmark CPU and GPU for all operating systems
Home-page: https://github.com/rameezrz25/SysBenchInfo
Author: rameezrz25
Author-email: rameezrz25@gmail.com
Classifier: Programming Language :: Python :: 3
Classifier: License :: OSI Approved :: MIT License
Classifier: Operating System :: OS Independent
Requires-Python: >=3.10
Requires-Dist: psutil
Requires-Dist: GPUtil
Requires-Dist: tabulate
